scanpy_clustering/__init__.py
scanpy_clustering/clustering.py
scanpy_clustering/_c_ext/__init__.py
scanpy_clustering/algorithms/__init__.py
scanpy_clustering/algorithms/base.py
scanpy_clustering/algorithms/dbScan.py
scanpy_clustering/algorithms/dbScan_Base.py
scanpy_clustering-0.1.0.dist-info/LICENSE
scanpy_clustering-0.1.0.dist-info/METADATA
scanpy_clustering-0.1.0.dist-info/WHEEL
scanpy_clustering-0.1.0.dist-info/top_level.txt
scanpy_clustering-0.1.0.dist-info/RECORD
