Metadata-Version: 2.2
Name: scanpy_clustering
Version: 0.1.0
Summary: Modular clustering extension for scanpy
Author: Daniel Sutton
Requires-Python: >=3.8
License-File: LICENSE
Requires-Dist: scanpy>=1.9.0
Requires-Dist: numpy>=1.20.0
Requires-Dist: anndata>=0.8.0
Requires-Dist: scipy>=1.6.0
Dynamic: author
Dynamic: requires-dist
Dynamic: requires-python
Dynamic: summary
